{
    "key": "post_type_664a41ea41e7e",
    "title": "Salons",
    "menu_order": 0,
    "active": true,
    "post_type": "salon",
    "advanced_configuration": true,
    "import_source": "",
    "import_date": "",
    "labels": {
        "name": "Salons",
        "singular_name": "Salon",
        "menu_name": "Saloons",
        "all_items": "All Saloons",
        "edit_item": "Edit Salon",
        "view_item": "View Salon",
        "view_items": "View Saloons",
        "add_new_item": "Add New Salon",
        "add_new": "Add New Salon",
        "new_item": "New Salon",
        "parent_item_colon": "Parent Salon:",
        "search_items": "Search Saloons",
        "not_found": "No saloons found",
        "not_found_in_trash": "No saloons found in Trash",
        "archives": "Salon Archives",
        "attributes": "Salon Attributes",
        "featured_image": "",
        "set_featured_image": "",
        "remove_featured_image": "",
        "use_featured_image": "",
        "insert_into_item": "Insert into salon",
        "uploaded_to_this_item": "Uploaded to this salon",
        "filter_items_list": "Filter saloons list",
        "filter_by_date": "Filter saloons by date",
        "items_list_navigation": "Saloons list navigation",
        "items_list": "Saloons list",
        "item_published": "Salon published.",
        "item_published_privately": "Salon published privately.",
        "item_reverted_to_draft": "Salon reverted to draft.",
        "item_scheduled": "Salon scheduled.",
        "item_updated": "Salon updated.",
        "item_link": "Salon Link",
        "item_link_description": "A link to a salon."
    },
    "description": "",
    "public": true,
    "hierarchical": false,
    "exclude_from_search": false,
    "publicly_queryable": true,
    "show_ui": true,
    "show_in_menu": true,
    "admin_menu_parent": "",
    "show_in_admin_bar": true,
    "show_in_nav_menus": true,
    "show_in_rest": true,
    "rest_base": "",
    "rest_namespace": "wp\/v2",
    "rest_controller_class": "WP_REST_Posts_Controller",
    "menu_position": "",
    "menu_icon": "",
    "rename_capabilities": false,
    "singular_capability_name": "post",
    "plural_capability_name": "posts",
    "supports": [
        "title",
        "thumbnail"
    ],
    "taxonomies": "",
    "has_archive": false,
    "has_archive_slug": "",
    "rewrite": {
        "permalink_rewrite": "post_type_key",
        "with_front": "1",
        "feeds": "0",
        "pages": "1"
    },
    "query_var": "post_type_key",
    "query_var_name": "",
    "can_export": true,
    "delete_with_user": false,
    "register_meta_box_cb": "",
    "enter_title_here": "",
    "modified": 1716142686
}
